xkits/__init__.py
xkits/actuator.py
xkits/attribute.py
xkits/cache.py
xkits/colorful.py
xkits/complete.py
xkits/executor.py
xkits/logger.py
xkits/meter.py
xkits/parser.py
xkits/project.py
xkits/safefile.py
xkits/scanner.py
xkits/sheet.py
xkits/sitepage.py
xkits/thread.py
xkits/utils.py
xkits-2.7.0.dist-info/LICENSE
xkits-2.7.0.dist-info/METADATA
xkits-2.7.0.dist-info/WHEEL
xkits-2.7.0.dist-info/entry_points.txt
xkits-2.7.0.dist-info/top_level.txt
xkits-2.7.0.dist-info/zip-safe
xkits-2.7.0.dist-info/RECORD
