Metadata-Version: 2.1
Name: xkits
Version: 2.7.0
Summary: Python toolkit.
Home-page: https://github.com/bondbox/xkits/
Author: Mingzhe Zou
Author-email: zoumingzhe@outlook.com
License: MIT
Project-URL: Source Code, https://github.com/bondbox/xkits/
Project-URL: Bug Tracker, https://github.com/bondbox/xkits/issues
Project-URL: Documentation, https://github.com/bondbox/xkits/
Keywords: command,command-line,argparse,argcomplete,completion,xarg,colorama,colorlog,termainal
Platform: any
Classifier: Programming Language :: Python
Classifier: Programming Language :: Python :: 3
License-File: LICENSE
Requires-Dist: argcomplete >=3.2.1
Requires-Dist: colorama
Requires-Dist: colorlog
Requires-Dist: filelock
Requires-Dist: openpyxl
Requires-Dist: tabulate
Requires-Dist: wcwidth
Requires-Dist: xlrd
Requires-Dist: xlwt
Requires-Dist: requests
Requires-Dist: beautifulsoup4
